st_text_annotator/__init__.py
streamlit_text_annotator-0.1.4.dist-info/LICENSE
streamlit_text_annotator-0.1.4.dist-info/METADATA
streamlit_text_annotator-0.1.4.dist-info/WHEEL
streamlit_text_annotator-0.1.4.dist-info/top_level.txt
streamlit_text_annotator-0.1.4.dist-info/RECORD
