Metadata-Version: 2.1
Name: streamlit-text-annotator
Version: 0.1.4
Summary: Component for annotating text for NLP resolution
Home-page: https://github.com/rmarquet21/steamlit-text-annotator
Author: Robin Marquet
Author-email: Robin Marquet <robin.marquet3@gmail.com>
Project-URL: Homepage, https://github.com/rmarquet21/streamlit-text-annotator
Project-URL: Bug Tracker, https://github.com/rmarquet21/streamlit-text-annotator/issues
Classifier: Programming Language :: Python :: 3
Classifier: License :: OSI Approved :: MIT License
Classifier: Operating System :: OS Independent
Requires-Python: >=3.8
License-File: LICENSE
Requires-Dist: streamlit (>=1.0.0)
